chat-client.py
chat-server.py
utils.py
console_chat_dsima-0.0.1.dist-info/LICENSE.txt
console_chat_dsima-0.0.1.dist-info/METADATA
console_chat_dsima-0.0.1.dist-info/WHEEL
console_chat_dsima-0.0.1.dist-info/top_level.txt
console_chat_dsima-0.0.1.dist-info/RECORD
