Metadata-Version: 2.1
Name: console-chat-dsima
Version: 0.0.1
Summary: Console chat.
Home-page: https://github.com/danilasimanok/ConsoleChat
Author: Danila Simanok
Author-email: danilasimanok@gmail.com
License: UNKNOWN
Platform: UNKNOWN
Classifier: Programming Language :: Python :: 3.8
Classifier: License :: OSI Approved :: MIT License
Classifier: Operating System :: POSIX :: Linux
